{
  "proposalId": "p-ghi",
  "companyName": "C사",
  "totalScore": 92.0,
  "maxScore": 100,
  "createdAt": "2025-10-01T14:35:00Z",
  "status": "completed",
  "progress": 100,
  "estNextUpdateSec": 0,
  "rubricItems": [
    {
      "key": "security",
      "label": "보안 아키텍처 적합성",
      "max": 20,
      "score": 19,
      "rationale": "엔터프라이즈급 보안 아키텍처를 제안했습니다. Zero Trust 보안 모델, 다층 방어 체계, 고급 위협 탐지 시스템(ATP)을 모두 포함하고 있습니다. ISO 27001, SOC 2 인증 획득 계획이 구체적으로 명시되어 있습니다.\n\n암호화 키 관리 시스템(KMS)과 시크릿 관리가 탁월하며, DevSecOps 프로세스가 개발 라이프사이클 전반에 통합되어 있습니다. 보안 사고 대응 절차(Incident Response Plan)도 상세히 기술되어 있습니다."
    },
    {
      "key": "scalability",
      "label": "확장성 및 성능",
      "max": 20,
      "score": 18,
      "rationale": "클라우드 네이티브 아키텍처로 무제한에 가까운 확장성을 제공합니다. 서버리스 컴퓨팅과 컨테이너를 적절히 조합하여 비용 효율적인 확장이 가능합니다.\n\nGlobal CDN 구성과 멀티 리전 배포로 전 세계 어디서나 낮은 지연시간을 보장합니다. 성능 테스트 결과(부하 테스트, 스트레스 테스트)를 포함하여 신뢰도가 높습니다."
    },
    {
      "key": "usability",
      "label": "사용성 및 UI/UX",
      "max": 15,
      "score": 15,
      "rationale": "최고 수준의 UX 디자인을 제공합니다. 사용자 리서치를 기반으로 한 페르소나 설정, 사용자 여정 맵핑이 우수하며, WCAG 2.1 AAA 수준의 접근성을 목표로 합니다.\n\n직관적인 인터페이스, 일관된 디자인 시스템, 상세한 인터랙션 가이드를 제공합니다. 다국어 지원(10개 언어)과 다크 모드가 기본 제공됩니다."
    },
    {
      "key": "integration",
      "label": "기존 시스템 연동",
      "max": 15,
      "score": 14,
      "rationale": "REST, GraphQL, gRPC를 모두 지원하는 유연한 API 전략을 제시했습니다. 주요 엔터프라이즈 시스템(SAP, Salesforce, Oracle 등)과의 사전 검증된 커넥터를 제공합니다.\n\n무중단 데이터 마이그레이션 전략과 롤백 계획이 상세하며, 실시간 양방향 동기화를 지원합니다. ETL 파이프라인 구성이 우수합니다."
    },
    {
      "key": "cost",
      "label": "비용 효율성",
      "max": 15,
      "score": 13,
      "rationale": "초기 투자 비용은 다른 제안 대비 다소 높으나, 5년 TCO 분석에서 가장 경제적입니다. FinOps 전략을 통해 클라우드 비용을 지속적으로 최적화합니다.\n\nAI 기반 자원 예측으로 불필요한 비용을 제거하며, Reserved 및 Savings Plan을 통해 최대 40% 비용 절감이 가능합니다. ROI가 2년 차에 달성될 것으로 예상됩니다."
    },
    {
      "key": "timeline",
      "label": "일정 및 이행 계획",
      "max": 15,
      "score": 13,
      "rationale": "5개월의 공격적이지만 실현 가능한 일정을 제시했습니다. Agile 방법론을 적용하여 2주 단위 스프린트로 진행하며, 각 스프린트마다 실행 가능한 제품을 제공합니다.\n\nCI/CD 파이프라인이 초기부터 구축되어 빠른 반복이 가능합니다. 다만, 일부 고급 기능(AI 기반 추천 등)은 2단계로 연기되어 초기 범위가 축소되었습니다."
    }
  ],
  "highlights": [
    "최고 수준의 보안 및 확장성 (19/20, 18/20)",
    "완벽한 사용성 달성 (15/15)",
    "엔터프라이즈급 시스템 연동 지원",
    "장기 TCO 측면에서 가장 경제적"
  ],
  "risks": [
    "초기 투자 비용 부담",
    "일부 고급 기능 2단계로 연기"
  ]
}

